{
  "_note": "Le vœu, écrit autrefois dans le carnet de Mamy, se reconstitue fragment par fragment.",
  "order": [
    "fragment_01", "fragment_02", "fragment_03", "fragment_04",
    "fragment_05", "fragment_06", "fragment_07", "fragment_08",
    "fragment_09", "fragment_10", "fragment_11", "fragment_12",
    "fragment_13"
  ],
  "fragments": {
    "fragment_01": { "text": "« Je voudrais que ceux que j'aime n'oublient jamais… »", "from": "mamy" },
    "fragment_02": { "text": "« …les trésors qu'on déniche à deux, »", "from": "alois" },
    "fragment_03": { "text": "« les mains qui savent tout réparer, »", "from": "xavier" },
    "fragment_04": { "text": "« les graines plantées avec patience, »", "from": "papy" },
    "fragment_05": { "text": "« les parties qu'on recommence encore, »", "from": "jules" },
    "fragment_06": { "text": "« les histoires lues à mi-voix, »", "from": "oxane" },
    "fragment_07": { "text": "« les musiques qu'on invente le soir, »", "from": "cyril" },
    "fragment_08": { "text": "« les moteurs qui repartent toujours, »", "from": "manu" },
    "fragment_09": { "text": "« les tables où chacun a sa place, »", "from": "noelia" },
    "fragment_10": { "text": "« les danses au bord de la rivière, »", "from": "lo" },
    "fragment_11": { "text": "« les étoiles qu'on compte ensemble, »", "from": "lana" },
    "fragment_12": { "text": "« les animaux qui connaissent nos secrets, »", "from": "marjo" },
    "fragment_13": { "text": "« …et que jamais, jamais, notre village ne cesse de chanter. »", "from": "mousquetaires" }
  }
}
